cloud/__init__.py
oscillink/__init__.py
oscillink/cli.py
oscillink/py.typed
oscillink-0.1.13.dist-info/licenses/LICENSE
oscillink-0.1.13.dist-info/licenses/NOTICE
oscillink-0.1.13.dist-info/METADATA
oscillink-0.1.13.dist-info/WHEEL
oscillink-0.1.13.dist-info/entry_points.txt
oscillink-0.1.13.dist-info/top_level.txt
oscillink-0.1.13.dist-info/RECORD
